smkml/__init__.py
smkml/smk.py
smkml-1.0.0.dist-info/METADATA
smkml-1.0.0.dist-info/WHEEL
smkml-1.0.0.dist-info/top_level.txt
smkml-1.0.0.dist-info/RECORD
