Metadata-Version: 2.1
Name: smkml
Version: 1.0.0
Summary: A hybrid ML algorithm combining SVM and K-Means for classification and clustering.
Home-page: https://github.com/yourgithub/smkml
Author: Vansh Gautam
Author-email: vanshgautam2005@gmail.com
Classifier: Programming Language :: Python :: 3
Classifier: License :: OSI Approved :: MIT License
Classifier: Operating System :: OS Independent
Requires-Python: >=3.6
Requires-Dist: numpy
Requires-Dist: scikit-learn
